intnan/__init__.py
intnan/_version.py
intnan/intnan_np.py
intnan/intnan_numba.py
intnan/tests/__init__.py
intnan/tests/test_generic.py
intnan-0.2.1.dist-info/LICENSE.txt
intnan-0.2.1.dist-info/METADATA
intnan-0.2.1.dist-info/WHEEL
intnan-0.2.1.dist-info/top_level.txt
intnan-0.2.1.dist-info/RECORD
