Metadata-Version: 2.1
Name: intnan
Version: 0.2.1
Summary: Function collection for handling integers with NaNs.
Author-email: Michael Löffler <ml@occam.com.ua>
License: BSD 2-Clause License
Project-URL: source, https://github.com/ml31415/intnan
Project-URL: tracker, https://github.com/ml31415/intnan/issues
Keywords: integer,nan,missing values,intnan
Classifier: Development Status :: 4 - Beta
Classifier: Intended Audience :: Science/Research
Classifier: Intended Audience :: Developers
Classifier: Operating System :: OS Independent
Classifier: Programming Language :: Python :: 3
Classifier: Programming Language :: Python :: 3.9
Classifier: Programming Language :: Python :: 3.10
Classifier: Programming Language :: Python :: 3.11
Classifier: Topic :: Scientific/Engineering
Classifier: Topic :: Software Development :: Libraries
Classifier: License :: OSI Approved :: BSD License
Requires-Python: >=3.9
License-File: LICENSE.txt
Requires-Dist: numpy
Provides-Extra: dev
Requires-Dist: pytest ; extra == 'dev'
Requires-Dist: flake8 ; extra == 'dev'
Requires-Dist: numba ; extra == 'dev'
